fluent_alchemy/__init__.py
fluent_alchemy/activerecord.py
fluent_alchemy/builders/__init__.py
fluent_alchemy/builders/base.py
fluent_alchemy/builders/delete.py
fluent_alchemy/builders/insert.py
fluent_alchemy/builders/query.py
fluent_alchemy/builders/select.py
fluent_alchemy/mixins/__init__.py
fluent_alchemy/mixins/softdelete.py
fluent_alchemy/mixins/timestamp.py
fluent_alchemy/scopes/__init__.py
fluent_alchemy/scopes/softdelete.py
fluent_alchemy/session.py
fluent_alchemy-0.0.2.dist-info/LICENSE
fluent_alchemy-0.0.2.dist-info/METADATA
fluent_alchemy-0.0.2.dist-info/WHEEL
fluent_alchemy-0.0.2.dist-info/RECORD
