Metadata-Version: 2.1
Name: fluent-alchemy
Version: 0.0.2
Summary: Use SQLAlchemy fluently
Home-page: https://github.com/turisesonia/fluent-alchemy
License: MIT
Keywords: sqlalchemy,SQLAlchemy,activerecord,Active Record
Author: Sam Yao
Author-email: turisesonia@gmail.com
Requires-Python: >=3.8,<4.0
Classifier: License :: OSI Approved :: MIT License
Classifier: Programming Language :: Python :: 3
Classifier: Programming Language :: Python :: 3.8
Classifier: Programming Language :: Python :: 3.9
Classifier: Programming Language :: Python :: 3.10
Classifier: Programming Language :: Python :: 3.11
Classifier: Programming Language :: Python :: 3.12
Requires-Dist: sqlalchemy (>=2.0,<3.0)
Project-URL: Documentation, https://github.com/turisesonia/fluent-alchemy
Project-URL: Repository, https://github.com/turisesonia/fluent-alchemy
